modconf/__init__.py
modconf/tests/test_class.py
modconf-0.3.0.dist-info/DESCRIPTION.rst
modconf-0.3.0.dist-info/METADATA
modconf-0.3.0.dist-info/RECORD
modconf-0.3.0.dist-info/WHEEL
modconf-0.3.0.dist-info/metadata.json
modconf-0.3.0.dist-info/top_level.txt
