Metadata-Version: 2.0
Name: modconf
Version: 0.3.0
Summary: pattern for using python modules as configuration files
Home-page: http://github.com/chuck1/modconf
Author: Charles Rymal
Author-email: charlesrymal@gmail.com
License: MIT
Platform: UNKNOWN
Requires-Dist: pkgtool (==0.1b52)
Requires-Dist: py (==1.4.34)
Requires-Dist: pytest (==3.1.2)
Requires-Dist: termcolor (==1.1.0)
Requires-Dist: toml (==0.9.2)
